nvidia/__init__.py
nvidia/nvimgcodec/__init__.py
nvidia/nvimgcodec/nvimgcodec_0.dll
nvidia/nvimgcodec/nvimgcodec_impl.cp310-win_amd64.pyd
nvidia/nvimgcodec/nvimgcodec_impl.cp311-win_amd64.pyd
nvidia/nvimgcodec/nvimgcodec_impl.cp312-win_amd64.pyd
nvidia/nvimgcodec/nvimgcodec_impl.cp313-win_amd64.pyd
nvidia/nvimgcodec/nvimgcodec_impl.cp38-win_amd64.pyd
nvidia/nvimgcodec/nvimgcodec_impl.cp39-win_amd64.pyd
nvidia/nvimgcodec/extensions/libjpeg_turbo_ext_0.dll
nvidia/nvimgcodec/extensions/libtiff_ext_0.dll
nvidia/nvimgcodec/extensions/nvbmp_ext_0.dll
nvidia/nvimgcodec/extensions/nvjpeg2k_ext_0.dll
nvidia/nvimgcodec/extensions/nvjpeg_ext_0.dll
nvidia/nvimgcodec/extensions/nvpnm_ext_0.dll
nvidia/nvimgcodec/extensions/nvtiff_ext_0.dll
nvidia/nvimgcodec/extensions/opencv_ext_0.dll
nvidia/nvimgcodec/include/nvcv_adapter.hpp
nvidia/nvimgcodec/include/nvimgcodec.h
nvidia/nvimgcodec/include/nvimgcodec_version.h
nvidia_nvimgcodec_cu13-0.6.1.37.dist-info/licenses/LICENSE.txt
nvidia_nvimgcodec_cu13-0.6.1.37.dist-info/METADATA
nvidia_nvimgcodec_cu13-0.6.1.37.dist-info/WHEEL
nvidia_nvimgcodec_cu13-0.6.1.37.dist-info/top_level.txt
nvidia_nvimgcodec_cu13-0.6.1.37.dist-info/RECORD
